paste/__init__.py
paste/admin.py
paste/apps.py
paste/constants.py
paste/models.py
paste/permissions.py
paste/serializers.py
paste/urls.py
paste/views.py
django_paste-1.1.3.dist-info/LICENSE
django_paste-1.1.3.dist-info/METADATA
django_paste-1.1.3.dist-info/WHEEL
django_paste-1.1.3.dist-info/top_level.txt
django_paste-1.1.3.dist-info/RECORD
